pydm/__init__.py
pydm/_version.py
pydm/application.py
pydm/config.py
pydm/default_stylesheet.qss
pydm/display.py
pydm/display_module.py
pydm/exception.py
pydm/main_window.py
pydm/pydm.ui
pydm/pydm_ui.py
pydm/qtdesigner.py
pydm/register_pydm_designer_plugin.py
pydm/PyQt/Qt.py
pydm/PyQt/QtCore.py
pydm/PyQt/QtDesigner.py
pydm/PyQt/QtGui.py
pydm/PyQt/QtSvg.py
pydm/PyQt/QtWidgets.py
pydm/PyQt/__init__.py
pydm/PyQt/uic.py
pydm/about_pydm/__init__.py
pydm/about_pydm/about.py
pydm/about_pydm/about.ui
pydm/about_pydm/about_ui.py
pydm/about_pydm/contributors.txt
pydm/about_pydm/print_contributors_github_usernames.sh
pydm/connection_inspector/__init__.py
pydm/connection_inspector/connection_inspector.py
pydm/connection_inspector/connection_table_model.py
pydm/data_plugins/__init__.py
pydm/data_plugins/archiver_plugin.py
pydm/data_plugins/calc_plugin.py
pydm/data_plugins/epics_plugin.py
pydm/data_plugins/fake_plugin.py
pydm/data_plugins/local_plugin.py
pydm/data_plugins/plugin.py
pydm/data_plugins/pva_plugin.py
pydm/data_plugins/epics_plugins/__init__.py
pydm/data_plugins/epics_plugins/caproto_plugin_component.py
pydm/data_plugins/epics_plugins/p4p_plugin_component.py
pydm/data_plugins/epics_plugins/psp_plugin_component.py
pydm/data_plugins/epics_plugins/pva_codec.py
pydm/data_plugins/epics_plugins/pyepics_plugin_component.py
pydm/help_files/__init__.py
pydm/help_files/help_window.py
pydm/show_macros/__init__.py
pydm/show_macros/show_macros.py
pydm/tests/__init__.py
pydm/tests/conftest.py
pydm/tests/test_about_screen.py
pydm/tests/test_data_plugins_import.py
pydm/tests/test_display.py
pydm/tests/test_main_window.py
pydm/tests/test_plugins_import.py
pydm/tests/test_show_macros.py
pydm/tests/test_tools.py
pydm/tests/data_plugins/test_archiver_plugin.py
pydm/tests/data_plugins/test_calc_plugin.py
pydm/tests/data_plugins/test_p4p_plugin_component.py
pydm/tests/data_plugins/test_plugin.py
pydm/tests/data_plugins/test_psp_plugin_component.py
pydm-1.28.1.dist-info/licenses/LICENSE.md
pydm-1.28.1.dist-info/METADATA
pydm-1.28.1.dist-info/WHEEL
pydm-1.28.1.dist-info/entry_points.txt
pydm-1.28.1.dist-info/top_level.txt
pydm-1.28.1.dist-info/RECORD
