Metadata-Version: 2.4
Name: pydm
Version: 1.28.1
Summary: A PyQt-based framework for building user interfaces for control systems
Author: SLAC National Accelerator Laboratory
License: Copyright (c) 2017-2025, The Board of Trustees of the Leland Stanford
Project-URL: Homepage, https://github.com/slaclab/pydm
Project-URL: Documentation, https://slaclab.github.io/pydm/
Classifier: Development Status :: 5 - Production/Stable
Classifier: Natural Language :: English
Classifier: Programming Language :: Python :: 3
Classifier: Operating System :: OS Independent
Requires-Python: >=3.10
License-File: LICENSE.md
Requires-Dist: entrypoints
Requires-Dist: numpy>=1.11.0
Requires-Dist: pyepics>=3.2.7
Requires-Dist: pyqtgraph>=0.12.0
Requires-Dist: qtpy>=2.2.0
Requires-Dist: scipy>=0.12.0
Requires-Dist: six
Provides-Extra: test
Requires-Dist: codecov; extra == "test"
Requires-Dist: pytest>=3.6; extra == "test"
Requires-Dist: pytest-qt; extra == "test"
Requires-Dist: pytest-cov; extra == "test"
Requires-Dist: pytest-timeout; extra == "test"
Requires-Dist: p4p; extra == "test"
Requires-Dist: pre-commit; extra == "test"
Provides-Extra: test-no-optional
Requires-Dist: codecov; extra == "test-no-optional"
Requires-Dist: pytest>=3.6; extra == "test-no-optional"
Requires-Dist: pytest-qt; extra == "test-no-optional"
Requires-Dist: pytest-cov; extra == "test-no-optional"
Requires-Dist: pytest-timeout; extra == "test-no-optional"
Provides-Extra: doc
Requires-Dist: doctr; extra == "doc"
Requires-Dist: sphinx==5.3.0; extra == "doc"
Requires-Dist: sphinx_rtd_theme; extra == "doc"
Requires-Dist: sphinxcontrib-napoleon; extra == "doc"
Dynamic: license-file
